LICENSE.txt
MANIFEST.in
README.rst
setup.py
spotlightpy/__init__.py
spotlightpy/spotlight.py
spotlightpy.egg-info/PKG-INFO
spotlightpy.egg-info/SOURCES.txt
spotlightpy.egg-info/dependency_links.txt
spotlightpy.egg-info/not-zip-safe
spotlightpy.egg-info/requires.txt
spotlightpy.egg-info/top_level.txt