Metadata-Version: 1.1
Name: spotlightpy
Version: 0.6
Summary: Extract Images from Microsoft Spotlight Project(Windows X only)
Home-page: https://github.com/joshikunal94/spotlightpy
Author: Kunal Joshi
Author-email: joshikunal16@gmail.com
License: MIT
Keywords: spotlight Microsoft Windows10 HDImages
Platform: UNKNOWN
Classifier: Development Status :: 5 - Production/Stable
Classifier: License :: OSI Approved :: MIT License
Classifier: Programming Language :: Python :: 3 :: Only
Classifier: Operating System :: Microsoft :: Windows
